jupyterlab_remote_contents/__init__.py
jupyterlab_remote_contents/_version.py
jupyterlab_remote_contents/labextension/package.json
jupyterlab_remote_contents/labextension/static/747.a6cbd3eef3ab97de30d2.js
jupyterlab_remote_contents/labextension/static/809.188526886475a418cfb2.js
jupyterlab_remote_contents/labextension/static/remoteEntry.2b86a26b9586a62ca9ef.js
jupyterlab_remote_contents/labextension/static/style.js
jupyterlab_remote_contents/labextension/static/third-party-licenses.json
jupyterlab_remote_contents-0.1.1.data/data/share/jupyter/labextensions/jupyterlab-remote-contents/package.json
jupyterlab_remote_contents-0.1.1.data/data/share/jupyter/labextensions/jupyterlab-remote-contents/static/747.a6cbd3eef3ab97de30d2.js
jupyterlab_remote_contents-0.1.1.data/data/share/jupyter/labextensions/jupyterlab-remote-contents/static/809.188526886475a418cfb2.js
jupyterlab_remote_contents-0.1.1.data/data/share/jupyter/labextensions/jupyterlab-remote-contents/static/remoteEntry.2b86a26b9586a62ca9ef.js
jupyterlab_remote_contents-0.1.1.data/data/share/jupyter/labextensions/jupyterlab-remote-contents/static/style.js
jupyterlab_remote_contents-0.1.1.data/data/share/jupyter/labextensions/jupyterlab-remote-contents/static/third-party-licenses.json
jupyterlab_remote_contents-0.1.1.data/data/share/jupyter/labextensions/jupyterlab-remote-contents/install.json
jupyterlab_remote_contents-0.1.1.dist-info/METADATA
jupyterlab_remote_contents-0.1.1.dist-info/WHEEL
jupyterlab_remote_contents-0.1.1.dist-info/licenses/LICENSE
jupyterlab_remote_contents-0.1.1.dist-info/RECORD
