Metadata-Version: 2.1
Name: jupyterlab-remote-contents
Version: 0.1.1
Summary: Access remote files through a Jupyter server
Project-URL: Homepage, https://github.com/davidbrochart/jupyterlab-remote-contents
Project-URL: Bug Tracker, https://github.com/davidbrochart/jupyterlab-remote-contents/issues
Project-URL: Repository, https://github.com/davidbrochart/jupyterlab-remote-contents.git
Author: JupyterLab Contrib Team
License: BSD 3-Clause License
License-File: LICENSE
Classifier: Framework :: Jupyter
Classifier: Framework :: Jupyter :: JupyterLab
Classifier: Framework :: Jupyter :: JupyterLab :: 4
Classifier: Framework :: Jupyter :: JupyterLab :: Extensions
Classifier: Framework :: Jupyter :: JupyterLab :: Extensions :: Prebuilt
Classifier: License :: OSI Approved :: BSD License
Classifier: Programming Language :: Python
Classifier: Programming Language :: Python :: 3
Classifier: Programming Language :: Python :: 3.7
Classifier: Programming Language :: Python :: 3.8
Classifier: Programming Language :: Python :: 3.9
Classifier: Programming Language :: Python :: 3.10
Classifier: Programming Language :: Python :: 3.11
Requires-Python: >=3.7
